flake8_if_statements/__init__.py
flake8_if_statements/errors.py
flake8_if_statements/plugin.py
flake8_if_statements/visitor.py
flake8_if_statements-1.0.0.dist-info/entry_points.txt
flake8_if_statements-1.0.0.dist-info/LICENSE
flake8_if_statements-1.0.0.dist-info/WHEEL
flake8_if_statements-1.0.0.dist-info/METADATA
flake8_if_statements-1.0.0.dist-info/RECORD
