Metadata-Version: 2.1
Name: flake8-if-statements
Version: 1.0.0
Summary: Flake8 linter for if statements
Home-page: https://pypi.org/project/flake8-if-statements
License: MIT
Author: David S
Author-email: d1618033@gmail.com
Requires-Python: >=3.7,<4.0
Classifier: License :: OSI Approved :: MIT License
Classifier: Programming Language :: Python :: 3
Classifier: Programming Language :: Python :: 3.7
Classifier: Programming Language :: Python :: 3.8
Classifier: Programming Language :: Python :: 3.9
Classifier: Programming Language :: Python :: 3.10
Requires-Dist: astor (>=0.8.1,<0.9.0)
Requires-Dist: flake8-plugin-utils (>=1.2.0,<2.0.0)
Project-URL: Repository, https://github.com/d1618033/flake8-if-statements
